mcptool/__init__.py
mcptool/mcptool.py
openai_agents_mcptool-0.1.0.dist-info/LICENSE
openai_agents_mcptool-0.1.0.dist-info/METADATA
openai_agents_mcptool-0.1.0.dist-info/WHEEL
openai_agents_mcptool-0.1.0.dist-info/top_level.txt
openai_agents_mcptool-0.1.0.dist-info/RECORD
