Metadata-Version: 2.1
Name: openai-agents-mcptool
Version: 0.1.0
Summary: A tool for integrating MCP with OpenAI Agents SDK
Home-page: https://github.com/shadowcz007/openai-agents-mcptool
Author: shadow
Author-email: 389570357@qq.com
Classifier: Programming Language :: Python :: 3
Classifier: License :: OSI Approved :: MIT License
Classifier: Operating System :: OS Independent
Requires-Python: >=3.6
License-File: LICENSE
Requires-Dist: openai-agents
Requires-Dist: mcp
